monga/__init__.py
monga/aggregate.py
monga/count.py
monga/filter.py
monga/find.py
monga/find_one.py
monga/find_one_and_update.py
monga/insert_one.py
monga/monga.py
monga-0.0.5.dist-info/LICENSE
monga-0.0.5.dist-info/METADATA
monga-0.0.5.dist-info/WHEEL
monga-0.0.5.dist-info/top_level.txt
monga-0.0.5.dist-info/RECORD
